{
    "list": [
        {
            "name": "Albania",
            "code": "AL",
            "capital": "Tirana",
            "region": "EU",
            "currency": {
                "code": "ALL",
                "name": "Albanian lek",
                "symbol": "L"
            },
            "language": {
                "code": "sq",
                "name": "Albanian"
            },
            "flag": "http://via.placeholder.com/120x80"
        },
        {
            "name": "Algeria",
            "code": "DZ",
            "capital": "Algiers",
            "region": "AF",
            "currency": {
                "code": "DZD",
                "name": "Algerian dinar",
                "symbol": "د.ج"
            },
            "language": {
                "code": "ar",
                "name": "Arabic"
            },
            "flag": "http://via.placeholder.com/120x80"
        },
        {
            "name": "American Samoa",
            "code": "AS",
            "capital": "Pago Pago",
            "region": "OC",
            "currency": {
                "code": "USD",
                "name": "United State Dollar",
                "symbol": "$"
            },
            "language": {
                "code": "en",
                "name": "English"
            },
            "flag": "http://via.placeholder.com/120x80"
        },
        {
            "name": "Andorra",
            "code": "AD",
            "capital": "Andorra la Vella",
            "region": "EU",
            "currency": {
                "code": "EUR",
                "name": "Euro",
                "symbol": "€"
            },
            "language": {
                "code": "ca",
                "name": "Catalan"
            },
            "flag": "http://via.placeholder.com/120x80"
        },
        {
            "name": "Angola",
            "code": "AO",
            "capital": "Luanda",
            "region": "AF",
            "currency": {
                "code": "AOA",
                "name": "Angolan kwanza",
                "symbol": "Kz"
            },
            "language": {
                "code": "pt",
                "name": "Portuguese"
            },
            "flag": "http://via.placeholder.com/120x80"
        }
    ]
}